main/__init__.py
main/cli.py
commit_msg_regex_hook-0.0.2.dist-info/LICENSE
commit_msg_regex_hook-0.0.2.dist-info/METADATA
commit_msg_regex_hook-0.0.2.dist-info/WHEEL
commit_msg_regex_hook-0.0.2.dist-info/entry_points.txt
commit_msg_regex_hook-0.0.2.dist-info/top_level.txt
commit_msg_regex_hook-0.0.2.dist-info/RECORD
