Metadata-Version: 2.1
Name: commit-msg-regex-hook
Version: 0.0.2
Summary: Checks if commit message matches supplied regex
Home-page: https://github.com/dtaivpp/commit-msg-regex-hook.git
Author: David Tippett
License: MIT
Platform: UNKNOWN
Classifier: Programming Language :: Python :: 3
Classifier: License :: OSI Approved :: MIT License
Classifier: Operating System :: OS Independent
Requires-Python: >=3.6
License-File: LICENSE
